<Properties>
  <MonoDevelop.Ide.Workbench ActiveDocument="autoTestsProject/Tests/Lecturer/PositiveTests/TestingTests.cs">
    <Files>
      <File FileName="autoTestsProject/Tests/Lecturer/PositiveTests/TestingTests.cs" Line="436" Column="40" />
      <File FileName="autoTestsProject/Defaults.cs" Line="20" Column="1" />
      <File FileName="autoTestsProject/Tests/Lecturer/PositiveTests/QuestionTests.cs" Line="1" Column="1" />
    </Files>
    <Pads>
      <Pad Id="ProjectPad">
        <State name="__root__">
          <Node name="autoTestsProject" expanded="True">
            <Node name="autoTestsProject" expanded="True">
              <Node name="Enums" expanded="True" />
              <Node name="Tests" expanded="True">
                <Node name="Lecturer" expanded="True">
                  <Node name="NegativeTests" expanded="True" />
                  <Node name="PositiveTests" expanded="True">
                    <Node name="TestingTests.cs" selected="True" />
                  </Node>
                </Node>
                <Node name="Student" expanded="True">
                  <Node name="NegativeTests" expanded="True" />
                  <Node name="PositiveTests" expanded="True" />
                </Node>
              </Node>
            </Node>
          </Node>
        </State>
      </Pad>
      <Pad Id="MonoDevelop.UnitTesting.TestPad">
        <State name="__root__">
          <Node name="autoTestsProject" expanded="True">
            <Node name="autoTestsProject" expanded="True">
              <Node name="autoTestsProject.Tests.Lecturer.PositiveTests" expanded="True">
                <Node name="TestingTests" expanded="True">
                  <Node name="AccessDoingTest" expanded="True" />
                  <Node name="AddAccessToStudentInTest" selected="True" />
                </Node>
              </Node>
            </Node>
          </Node>
        </State>
      </Pad>
    </Pads>
  </MonoDevelop.Ide.Workbench>
  <MonoDevelop.Ide.ItemProperties.autoTestsProject PreferredExecutionTarget="MonoDevelop.Default" />
  <MonoDevelop.Ide.DebuggingService.PinnedWatches />
  <MonoDevelop.Ide.Workspace ActiveConfiguration="Debug" />
  <Debugger.DebugSourceFolders>
    <String>/Users/katekuzmich/Library/Caches/VisualStudio/8.0/Symbols/mono/mono/8c552e98bd60bcbc47f8cafbc8c34a9433516ac8</String>
  </Debugger.DebugSourceFolders>
  <MonoDevelop.Ide.DebuggingService.Breakpoints>
    <BreakpointStore>
      <Breakpoint file="/Users/katekuzmich/Documents/4course/autotestsProject/autoTestsProject/autoTestsProject/Tests/Lecturer/PositiveTests/TestingTests.cs" relfile="autoTestsProject/Tests/Lecturer/PositiveTests/TestingTests.cs" line="457" column="1" />
      <Breakpoint file="/Users/katekuzmich/Documents/4course/autotestsProject/autoTestsProject/autoTestsProject/Tests/Lecturer/PositiveTests/TestingTests.cs" relfile="autoTestsProject/Tests/Lecturer/PositiveTests/TestingTests.cs" line="445" column="1" />
    </BreakpointStore>
  </MonoDevelop.Ide.DebuggingService.Breakpoints>
  <MultiItemStartupConfigurations />
</Properties>