<Properties StartupConfiguration="{781C3877-FA1C-419C-8C84-4800E246D0C0}|Модульные тесты">
  <MonoDevelop.Ide.Workbench ActiveDocument="autoTestsProject/Tests/Lecturer/NegativeTests/SubjectTests.cs">
    <Files>
      <File FileName="autoTestsProject/DriverHelper.cs" Line="19" Column="73" />
      <File FileName="autoTestsProject/Tests/Lecturer/NegativeTests/SubjectTests.cs" Line="197" Column="63" />
    </Files>
    <Pads>
      <Pad Id="ProjectPad">
        <State name="__root__">
          <Node name="autoTestsProject" expanded="True">
            <Node name="autoTestsProject" expanded="True">
              <Node name="Tests" expanded="True">
                <Node name="Lecturer" expanded="True">
                  <Node name="NegativeTests" expanded="True">
                    <Node name="SubjectTests.cs" selected="True" />
                  </Node>
                  <Node name="PositiveTests" expanded="True" />
                </Node>
              </Node>
            </Node>
          </Node>
        </State>
      </Pad>
      <Pad Id="MonoDevelop.Debugger.WatchPad">
        <State />
      </Pad>
      <Pad Id="MonoDevelop.UnitTesting.TestPad">
        <State name="__root__">
          <Node name="autoTestsProject" expanded="True">
            <Node name="autoTestsProject" expanded="True">
              <Node name="autoTestsProject.Tests.Lecturer.NegativeTests" expanded="True">
                <Node name="SubjectTests" expanded="True">
                  <Node name="ErrorAddSubjectWithExistingData" selected="True" />
                </Node>
              </Node>
            </Node>
          </Node>
        </State>
      </Pad>
    </Pads>
  </MonoDevelop.Ide.Workbench>
  <MonoDevelop.Ide.ItemProperties.autoTestsProject PreferredExecutionTarget="MonoDevelop.Default" />
  <MonoDevelop.Ide.DebuggingService.PinnedWatches />
  <MonoDevelop.Ide.Workspace ActiveConfiguration="Debug" />
  <Debugger.DebugSourceFolders>
    <String>/Users/katekuzmich/Library/Caches/VisualStudio/8.0/Symbols/mono/mono/8c552e98bd60bcbc47f8cafbc8c34a9433516ac8</String>
  </Debugger.DebugSourceFolders>
  <MonoDevelop.Ide.DebuggingService.Breakpoints>
    <BreakpointStore>
      <Breakpoint file="/Users/katekuzmich/Documents/4course/autotestsProject/autoTestsProject/autoTestsProject/Tests/Lecturer/PositiveTests/SubjectTests.cs" relfile="autoTestsProject/Tests/Lecturer/PositiveTests/SubjectTests.cs" line="62" column="1" />
      <Breakpoint file="/Users/katekuzmich/Documents/4course/autotestsProject/autoTestsProject/autoTestsProject/Tests/Lecturer/NegativeTests/SubjectTests.cs" relfile="autoTestsProject/Tests/Lecturer/NegativeTests/SubjectTests.cs" line="66" column="1" />
      <Breakpoint file="/Users/katekuzmich/Documents/4course/autotestsProject/autoTestsProject/autoTestsProject/Tests/Lecturer/NegativeTests/SubjectTests.cs" relfile="autoTestsProject/Tests/Lecturer/NegativeTests/SubjectTests.cs" line="89" column="1" />
    </BreakpointStore>
  </MonoDevelop.Ide.DebuggingService.Breakpoints>
  <MultiItemStartupConfigurations />
</Properties>